./.gitignore
./PKG-INFO
./README.md
./py.typed
./pyproject.toml
./example/__init__.py
./example/openrouter_example.py
./example/pyproject.toml
./tests/__init__.py
./tests/test_openrouter_llm.py
./vision_agents/plugins/openrouter/__init__.py
./vision_agents/plugins/openrouter/openrouter_llm.py
vision_agents_plugins_openrouter-0.2.10.dist-info/METADATA
vision_agents_plugins_openrouter-0.2.10.dist-info/WHEEL
vision_agents_plugins_openrouter-0.2.10.dist-info/RECORD
